lick_detector/__init__.py
lick_detector/base.py
lick_detector/files.py
lick_detector/gui.py
lick_detector/reward.py
lick_detector/utils.py
lick_detector-0.1.1.dist-info/METADATA
lick_detector-0.1.1.dist-info/WHEEL
lick_detector-0.1.1.dist-info/RECORD
