Metadata-Version: 2.1
Name: lick-detector
Version: 0.1.1
Summary: 
Author: Mathis
Author-email: m.j.basler@uva.nl
Requires-Python: >=3.10,<4.0
Classifier: Programming Language :: Python :: 3
Classifier: Programming Language :: Python :: 3.10
Classifier: Programming Language :: Python :: 3.11
Requires-Dist: matplotlib (>=3.7.2,<4.0.0)
Requires-Dist: numpy (>=1.25.2,<2.0.0)
Requires-Dist: pandas (>=2.0.3,<3.0.0)
Requires-Dist: pyserial (>=3.5,<4.0)
Requires-Dist: scikit-learn (>=1.3.0,<2.0.0)
